synchronous_fifo.srcs/sources_1/new/syc_fifo.v
`timescale 1ns / 1ns
//////////////////////////////////////////////////////////////////////////////////
// Company: 
// Engineer: 
// 
// Create Date: 07/09/2025 10:23:48 AM
// Design Name: 
// Module Name: syc_fifo
// Project Name: 
// Target Devices: 
// Tool Versions: 
// Description: 
// 
// Dependencies: 
// 
// Revision:
// Revision 0.01 - File Created
// Additional Comments:
// 
//////////////////////////////////////////////////////////////////////////////////

module syc_fifo
    // Parameters section
    #( parameter FIFO_DEPTH = 8,
	   parameter DATA_WIDTH = 32)
    // Ports section   
	(input clk, 
     input rst_n,
     input cs,     // chip select	 
     input wr_en, 
     input rd_en, 
     input [DATA_WIDTH-1:0] data_in, 
     output reg [DATA_WIDTH-1:0] data_out, 
	 output empty,
	 output full); 

  localparam FIFO_DEPTH_LOG = $clog2(FIFO_DEPTH);// 
 // Declare a by-dimensional array to store the data
  reg [DATA_WIDTH-1:0] fifo [0:FIFO_DEPTH-1];// depth 8 => [0:7] 32 bit elements
	
	// Wr/Rd pointer have 1 extra bits at MSB
  reg [FIFO_DEPTH_LOG:0] write_pointer;//3:0
  reg [FIFO_DEPTH_LOG:0] read_pointer;//3:0

  //write
    always @(posedge clk or negedge rst_n) 
      begin
      if(!rst_n)//rst =0 system reset happens
		    write_pointer <= 0;
      else if (cs && wr_en && !full) begin
          fifo[write_pointer[FIFO_DEPTH_LOG-1:0]] <= data_in;
	       write_pointer <= write_pointer + 1'b1;
      end
      end
  
	//read
	always @(posedge clk or negedge rst_n) 
      begin
	    if(!rst_n)
		    read_pointer <= 0;
      else if (cs && rd_en && !empty) begin
          	data_out <= fifo[read_pointer[FIFO_DEPTH_LOG-1:0]];
	        read_pointer <= read_pointer + 1'b1;
      end
	end
	
	// Declare the empty/full logic
    assign empty = (read_pointer == write_pointer);
	assign full  = (read_pointer == {~write_pointer[FIFO_DEPTH_LOG], write_pointer[FIFO_DEPTH_LOG-1:0]});

  
  /*
    always @(posedge clk) begin
	    if (cs && wr_en && !full)
	        fifo[write_pointer[FIFO_DEPTH_LOG-1:0]] <= data_in;
	end
	
	always @(posedge clk or negedge rst_n) begin
	    if (!rst_n)
		    data_out <= 0;
		else if (cs && rd_en && !empty)
	        data_out <= fifo[read_pointer[FIFO_DEPTH_LOG-1:0]];
	end
*/
endmodule



// test bench for simulation verification 

`timescale 1ns/1ns
module fyc_fifo_tb();
	
	// Testbench variables
	parameter FIFO_DEPTH = 8;
	parameter DATA_WIDTH = 32;
    reg clk = 0; 
    reg rst_n;
    reg cs;	 
    reg wr_en;
    reg rd_en;
    reg [DATA_WIDTH-1:0] data_in;
    wire [DATA_WIDTH-1:0] data_out;
	wire empty;
	wire full;
	
    integer i;
	
	// Instantiate the DUT
	syc_fifo  
	    #(.FIFO_DEPTH(FIFO_DEPTH),
          .DATA_WIDTH(DATA_WIDTH))
        dut
  	    (.clk     (clk     ), 
         .rst_n   (rst_n   ),
         .cs      (cs      ),	 
         .wr_en   (wr_en   ), 
         .rd_en   (rd_en   ), 
         .data_in (data_in ), 
         .data_out(data_out), 
	     .empty   (empty   ),
	     .full    (full    ));

  	// Create the clock signal
	always begin #5 clk = ~clk; end
  
    task write_data(input [DATA_WIDTH-1:0] d_in);
	    begin
		    @(posedge clk); // sync to positive edge of clock
			cs = 1; wr_en = 1;
			data_in = d_in;
			$display($time, " write_data data_in = %0d", data_in);
			@(posedge clk);
		    cs = 1; wr_en = 0;
		end
	endtask
	
	task read_data();
	    begin
		    @(posedge clk);  // sync to positive edge of clock
			cs = 1; rd_en = 1;
			@(posedge clk);
			//#1;
		    $display($time, " read_data data_out = %0d", data_out);
		    cs = 1; rd_en = 0;
		end
	endtask
	

	
    // Create stimulus	  
    initial begin
	    #1; 
		rst_n = 0; rd_en = 0; wr_en = 0;
		
        @(posedge clk) 
		rst_n = 1;
		$display($time, "\n SCENARIO 1");
		write_data(1);
		write_data(10);
		write_data(100);
		read_data();
		read_data();
		read_data();
		//read_data();
		
        $display($time, "\n SCENARIO 2");
		for (i=0; i<FIFO_DEPTH; i=i+1) begin
		    write_data(2**i);
			read_data();        
		end

        $display($time, "\n SCENARIO 3");		
		for (i=0; i<=FIFO_DEPTH; i=i+1) begin
		    write_data(2**i);
		end
		
		for (i=0; i<FIFO_DEPTH; i=i+1) begin
			read_data();
		end
		
	    #40 $finish;
	end
  
  initial begin
    $dumpfile("dump.vcd"); $dumpvars;
  end
endmodule

synchronous_fifo.sim/sim_1/behav/xsim/dump.vcd
$date
   Wed Jul  9 10:38:34 2025
$end

$version
  2023.2
  $dumpfile ("dump.vcd") 
$end

$timescale
  1ps
$end

$scope module fyc_fifo_tb $end
$var reg 1 ! clk $end
$var reg 1 " rst_n $end
$var reg 1 # cs $end
$var reg 1 $ wr_en $end
$var reg 1 % rd_en $end
$var reg 32 & data_in [31:0] $end
$var wire 32 ' data_out [31:0] $end
$var wire 1 ( empty $end
$var wire 1 ) full $end
$var integer 32 * i [31:0] $end
$scope module dut $end
$var wire 1 + clk $end
$var wire 1 , rst_n $end
$var wire 1 - cs $end
$var wire 1 . wr_en $end
$var wire 1 / rd_en $end
$var wire 32 0 data_in [31:0] $end
$var reg 32 1 data_out [31:0] $end
$var wire 1 ( empty $end
$var wire 1 ) full $end
$var reg 4 2 write_pointer [3:0] $end
$var reg 4 3 read_pointer [3:0] $end
$upscope $end
$scope task write_data $end
$var reg 32 4 d_in [31:0] $end
$upscope $end
$scope task read_data $end
$upscope $end
$upscope $end
$enddefinitions $end

#0
$dumpvars
0!
x"
x#
x$
x%
bx &
bx '
x(
x)
bx *
0+
x,
x-
x.
x/
bx 0
bx 1
bx 2
bx 3
bx 4
$end

#1000
0"
0$
0%
1(
0)
0,
0.
0/
b0 2
b0 3

#5000
1!
1"
1+
1,
b1 4

#10000
0!
0+

#15000
1!
1#
1$
b1 &
0(
1+
1-
1.
b1 0
b1 2

#20000
0!
0+

#25000
1!
0$
1+
0.
b1010 4

#30000
0!
0+

#35000
1!
1$
b1010 &
1+
1.
b1010 0
b10 2

#40000
0!
0+

#45000
1!
0$
1+
0.
b1100100 4

#50000
0!
0+

#55000
1!
1$
b1100100 &
1+
1.
b1100100 0
b11 2

#60000
0!
0+

#65000
1!
0$
1+
0.

#70000
0!
0+

#75000
1!
1%
b1 '
1+
1/
b1 1
b1 3

#80000
0!
0+

#85000
1!
0%
1+
0/

#90000
0!
0+

#95000
1!
1%
b1010 '
1+
1/
b1010 1
b10 3

#100000
0!
0+

#105000
1!
0%
1+
0/

#110000
0!
0+

#115000
1!
1%
b1100100 '
1(
1+
1/
b1100100 1
b11 3

#120000
0!
0+

#125000
1!
0%
b0 *
1+
0/
b1 4

#130000
0!
0+

#135000
1!
1$
b1 &
0(
1+
1.
b1 0
b100 2

#140000
0!
0+

#145000
1!
0$
1+
0.

#150000
0!
0+

#155000
1!
1%
b1 '
1(
1+
1/
b1 1
b100 3

#160000
0!
0+

#165000
1!
0%
b1 *
1+
0/
b10 4

#170000
0!
0+

#175000
1!
1$
b10 &
0(
1+
1.
b10 0
b101 2

#180000
0!
0+

#185000
1!
0$
1+
0.

#190000
0!
0+

#195000
1!
1%
b10 '
1(
1+
1/
b10 1
b101 3

#200000
0!
0+

#205000
1!
0%
b10 *
1+
0/
b100 4

#210000
0!
0+

#215000
1!
1$
b100 &
0(
1+
1.
b100 0
b110 2

#220000
0!
0+

#225000
1!
0$
1+
0.

#230000
0!
0+

#235000
1!
1%
b100 '
1(
1+
1/
b100 1
b110 3

#240000
0!
0+

#245000
1!
0%
b11 *
1+
0/
b1000 4

#250000
0!
0+

#255000
1!
1$
b1000 &
0(
1+
1.
b1000 0
b111 2

#260000
0!
0+

#265000
1!
0$
1+
0.

#270000
0!
0+

#275000
1!
1%
b1000 '
1(
1+
1/
b1000 1
b111 3

#280000
0!
0+

#285000
1!
0%
b100 *
1+
0/
b10000 4

#290000
0!
0+

#295000
1!
1$
b10000 &
0(
1+
1.
b10000 0
b1000 2

#300000
0!
0+

#305000
1!
0$
1+
0.

#310000
0!
0+

#315000
1!
1%
b10000 '
1(
1+
1/
b10000 1
b1000 3

#320000
0!
0+

#325000
1!
0%
b101 *
1+
0/
b100000 4

#330000
0!
0+

#335000
1!
1$
b100000 &
0(
1+
1.
b100000 0
b1001 2

#340000
0!
0+

#345000
1!
0$
1+
0.

#350000
0!
0+

#355000
1!
1%
b100000 '
1(
1+
1/
b100000 1
b1001 3

#360000
0!
0+

#365000
1!
0%
b110 *
1+
0/
b1000000 4

#370000
0!
0+

#375000
1!
1$
b1000000 &
0(
1+
1.
b1000000 0
b1010 2

#380000
0!
0+

#385000
1!
0$
1+
0.

#390000
0!
0+

#395000
1!
1%
b1000000 '
1(
1+
1/
b1000000 1
b1010 3

#400000
0!
0+

#405000
1!
0%
b111 *
1+
0/
b10000000 4

#410000
0!
0+

#415000
1!
1$
b10000000 &
0(
1+
1.
b10000000 0
b1011 2

#420000
0!
0+

#425000
1!
0$
1+
0.

#430000
0!
0+

#435000
1!
1%
b10000000 '
1(
1+
1/
b10000000 1
b1011 3

#440000
0!
0+

#445000
1!
0%
b0 *
1+
0/
b1 4

#450000
0!
0+

#455000
1!
1$
b1 &
0(
1+
1.
b1 0
b1100 2

#460000
0!
0+

#465000
1!
0$
b1 *
1+
0.
b10 4

#470000
0!
0+

#475000
1!
1$
b10 &
1+
1.
b10 0
b1101 2

#480000
0!
0+

#485000
1!
0$
b10 *
1+
0.
b100 4

#490000
0!
0+

#495000
1!
1$
b100 &
1+
1.
b100 0
b1110 2

#500000
0!
0+

#505000
1!
0$
b11 *
1+
0.
b1000 4

#510000
0!
0+

#515000
1!
1$
b1000 &
1+
1.
b1000 0
b1111 2

#520000
0!
0+

#525000
1!
0$
b100 *
1+
0.
b10000 4

#530000
0!
0+

#535000
1!
1$
b10000 &
1+
1.
b10000 0
b0 2

#540000
0!
0+

#545000
1!
0$
b101 *
1+
0.
b100000 4

#550000
0!
0+

#555000
1!
1$
b100000 &
1+
1.
b100000 0
b1 2

#560000
0!
0+

#565000
1!
0$
b110 *
1+
0.
b1000000 4

#570000
0!
0+

#575000
1!
1$
b1000000 &
1+
1.
b1000000 0
b10 2

#580000
0!
0+

#585000
1!
0$
b111 *
1+
0.
b10000000 4

#590000
0!
0+

#595000
1!
1$
b10000000 &
1)
1+
1.
b10000000 0
b11 2

#600000
0!
0+

#605000
1!
0$
b1000 *
1+
0.
b100000000 4

#610000
0!
0+

#615000
1!
1$
b100000000 &
1+
1.
b100000000 0

#620000
0!
0+

#625000
1!
0$
b0 *
1+
0.

#630000
0!
0+

#635000
1!
1%
b1 '
0)
1+
1/
b1 1
b1100 3

#640000
0!
0+

#645000
1!
0%
b1 *
1+
0/

#650000
0!
0+

#655000
1!
1%
b10 '
1+
1/
b10 1
b1101 3

#660000
0!
0+

#665000
1!
0%
b10 *
1+
0/

#670000
0!
0+

#675000
1!
1%
b100 '
1+
1/
b100 1
b1110 3

#680000
0!
0+

#685000
1!
0%
b11 *
1+
0/

#690000
0!
0+

#695000
1!
1%
b1000 '
1+
1/
b1000 1
b1111 3

#700000
0!
0+

#705000
1!
0%
b100 *
1+
0/

#710000
0!
0+

#715000
1!
1%
b10000 '
1+
1/
b10000 1
b0 3

#720000
0!
0+

#725000
1!
0%
b101 *
1+
0/

#730000
0!
0+

#735000
1!
1%
b100000 '
1+
1/
b100000 1
b1 3

#740000
0!
0+

#745000
1!
0%
b110 *
1+
0/

#750000
0!
0+

#755000
1!
1%
b1000000 '
1+
1/
b1000000 1
b10 3

#760000
0!
0+

#765000
1!
0%
b111 *
1+
0/

#770000
0!
0+

#775000
1!
1%
b10000000 '
1(
1+
1/
b10000000 1
b11 3

#780000
0!
0+

#785000
1!
0%
b1000 *
1+
0/

